{
  "slug": "transforming-fire-to-water",
  "order": 20,
  "name": "Transforming Fire to Water",
  "galleryMedium": "טכניקה משולבת",
  "detailMedium": "טכניקה משולבת על נייר · יצירה מקורית",
  "description": "אש ומים נפגשים בתוך מבנה אחד ומשנים זה את זה. היצירה מתבוננת ביכולת של אנרגיה לעבור צורה בלי לאבד את מהותה.",
  "alt": "Transforming Fire to Water, דימוי סימטרי של אש ומים",
  "image": "/images/artworks/transforming-fire-to-water+WEB.webp",
  "thumb": "/images/gallery/transforming-fire-to-water+thumb.webp",
  "category": "mixed",
  "originalAvailable": false,
  "originalPrice": 0,
  "canvasAvailable": false
}
